odoo/addons/stock_picking_sale_order_link/README.rst
odoo/addons/stock_picking_sale_order_link/__init__.py
odoo/addons/stock_picking_sale_order_link/__manifest__.py
odoo/addons/stock_picking_sale_order_link/i18n/de.po
odoo/addons/stock_picking_sale_order_link/i18n/es.po
odoo/addons/stock_picking_sale_order_link/i18n/fr.po
odoo/addons/stock_picking_sale_order_link/i18n/hr.po
odoo/addons/stock_picking_sale_order_link/i18n/it.po
odoo/addons/stock_picking_sale_order_link/i18n/nl.po
odoo/addons/stock_picking_sale_order_link/i18n/pt_BR.po
odoo/addons/stock_picking_sale_order_link/i18n/stock_picking_sale_order_link.pot
odoo/addons/stock_picking_sale_order_link/i18n/zh_CN.po
odoo/addons/stock_picking_sale_order_link/models/__init__.py
odoo/addons/stock_picking_sale_order_link/models/stock_picking.py
odoo/addons/stock_picking_sale_order_link/readme/CONTRIBUTORS.md
odoo/addons/stock_picking_sale_order_link/readme/DESCRIPTION.md
odoo/addons/stock_picking_sale_order_link/readme/USAGE.md
odoo/addons/stock_picking_sale_order_link/static/description/icon.png
odoo/addons/stock_picking_sale_order_link/static/description/index.html
odoo/addons/stock_picking_sale_order_link/tests/__init__.py
odoo/addons/stock_picking_sale_order_link/tests/test_stock_picking_sale_order_link.py
odoo/addons/stock_picking_sale_order_link/views/stock_picking_view.xml
odoo_addon_stock_picking_sale_order_link-18.0.1.0.0.4.dist-info/METADATA
odoo_addon_stock_picking_sale_order_link-18.0.1.0.0.4.dist-info/WHEEL
odoo_addon_stock_picking_sale_order_link-18.0.1.0.0.4.dist-info/top_level.txt
odoo_addon_stock_picking_sale_order_link-18.0.1.0.0.4.dist-info/RECORD
